adoc_math/__init__.py
adoc_math/__main__.py
adoc_math/_common/__init__.py
adoc_math/_common/a_imports.py
adoc_math/_common/b_types.py
adoc_math/_common/c_constants.py
adoc_math/_common/d_exceptions.py
adoc_math/_common/e_utils.py
adoc_math/_setup/__main__.py
adoc_math/_setup/a_install.py
adoc_math/_setup/b_link.py
adoc_math/a_helpers.py
adoc_math/b_reading.py
adoc_math/c_parsing.py
adoc_math/d_mathjax_wrapper.js
adoc_math/e_svg_transforming.py
adoc_math/f_processing.py
adoc_math/g_output.py
adoc_math/i_impl.py
adoc_math-1.0.9.dist-info/entry_points.txt
adoc_math-1.0.9.dist-info/WHEEL
adoc_math-1.0.9.dist-info/METADATA
adoc_math-1.0.9.dist-info/RECORD
