Metadata-Version: 2.1
Name: adoc-math
Version: 1.0.9
Summary: Use MathJax (Latex or AsciiMath) in your AsciiDoc projects!
License: ISC
Keywords: tex,latex,mathjax,asciidoc,asciidoctor,katex,asciimath,asciidoctor-pdf
Author: Dominik Teiml
Requires-Python: >=3.7
Classifier: Programming Language :: Python :: 3
Classifier: Programming Language :: Python :: 3.10
Classifier: Programming Language :: Python :: 3.7
Classifier: Programming Language :: Python :: 3.8
Classifier: Programming Language :: Python :: 3.9
Classifier: Topic :: Text Editors :: Text Processing
Project-URL: Reposity, https://github.com/hacker-dom/adoc-math
